Metadata-Version: 1.1
Name: cleanmask
Version: 1.0.1
Summary: Creates a binary mask given a FITS image
Home-page: https://github.com/SpheMakh/cleanmask
Author: Sphesihle Makhathini
Author-email: sphemakh@gmail.com
License: ['GNU GPL v2']
Platform: UNKNOWN
Classifier: Development Status :: 3 - Alpha
Classifier: Intended Audience :: Science/Research
Classifier: License :: OSI Approved :: GNU General Public License v2 (GPLv2)
Classifier: Operating System :: POSIX :: Linux
Classifier: Programming Language :: Python
Classifier: Topic :: Scientific/Engineering :: Astronomy
